pose_annotator/__init__.py
pose_annotator/__main__.py
pose_annotator/utils.py
pose_annotator/gui/__init__.py
pose_annotator/gui/custom_widgets.py
pose_annotator/gui/default_config.yaml
pose_annotator/gui/main.py
pose_annotator/gui/mainwindow.py
pose_annotator-0.0.2.dist-info/METADATA
pose_annotator-0.0.2.dist-info/WHEEL
pose_annotator-0.0.2.dist-info/entry_points.txt
pose_annotator-0.0.2.dist-info/top_level.txt
pose_annotator-0.0.2.dist-info/RECORD
