Metadata-Version: 2.1
Name: pose-annotator
Version: 0.0.2
Summary: Keypoint annotation GUI
Home-page: https://github.com/jbohnslav/pose_annotator
Author: Jim Bohnslav
Author-email: jbohnslav@gmail.com
License: UNKNOWN
Platform: UNKNOWN
Classifier: Programming Language :: Python :: 3
Classifier: Operating System :: OS Independent
Requires-Python: >=3.6
Requires-Dist: matplotlib
Requires-Dist: numpy
Requires-Dist: omegaconf (>=2.0)
Requires-Dist: opencv-python-headless
Requires-Dist: pandas
Requires-Dist: PySide2 (>=5.15)
Requires-Dist: vidio (>=0.0.3)
